{"id": "upon", "metadata": {"operation": "retrieve", "provider": "Oxford University Press", "schema": "RetrieveEntry"}, "results": [{"id": "upon", "language": "en-gb", "lexicalEntries": [{"entries": [{"senses": [{"examples": [{"text": "it was based upon two principles"}, {"text": "a school's dependence upon parental support"}], "id": "m_en_gbus1113930.005"}]}], "language": "en-gb", "lexicalCategory": {"id": "preposition", "text": "Preposition"}, "text": "upon"}], "type": "headword", "word": "upon"}], "word": "upon"}